README.md
setup.cfg
setup.py
flaskipy/__init__.py
flaskipy/commands.py
flaskipy.egg-info/PKG-INFO
flaskipy.egg-info/SOURCES.txt
flaskipy.egg-info/dependency_links.txt
flaskipy.egg-info/entry_points.txt
flaskipy.egg-info/requires.txt
flaskipy.egg-info/top_level.txt
flaskipy/flaskipy_templates/README.txt
flaskipy/flaskipy_templates/__init__.txt
flaskipy/flaskipy_templates/config.txt
flaskipy/flaskipy_templates/config_ini.txt
flaskipy/flaskipy_templates/controller.txt
flaskipy/flaskipy_templates/controller_init.txt
flaskipy/flaskipy_templates/db.txt
flaskipy/flaskipy_templates/main.txt
flaskipy/flaskipy_templates/model.txt
flaskipy/flaskipy_templates/model_init.txt
flaskipy/flaskipy_templates/modules_init.txt
flaskipy/flaskipy_templates/requirements.txt
flaskipy/flaskipy_templates/route.txt