Metadata-Version: 1.2
Name: flaskipy
Version: 0.1.1
Summary: Flaskipy is a cli tool for building RESTFul API with Python-Flask
Home-page: https://github.com/osmangoninahid/flaskipy
Author: ['Osman Goni Nahid', 'Porimol Chandro']
Author-email: ['nirobshitol@gmail.com', 'porimolchandroroy@gmail.com']
License: MIT License
Keywords: Flask-RESTFul API,Generator,CLI,Flaskipy
Platform: UNKNOWN
Classifier: Development Status :: 2 - Pre-Alpha
Classifier: Intended Audience :: Developers
Classifier: License :: OSI Approved :: MIT License
Classifier: Programming Language :: Python :: 3.5
Classifier: Framework :: Flask
Requires-Python: >3.0.0
